inceptor/__init__.py
inceptor/cli.py
inceptor/core/DreamArchitect.py
inceptor/core/__init__.py
inceptor/core/context_extractor.py
inceptor/core/dream_architect.py
inceptor/core/enums.py
inceptor/core/models.py
inceptor/core/ollama_client.py
inceptor/core/prompt_templates.py
inceptor/core/utils.py
inceptor/inceptor.py
inceptor/prompts.py
inceptor/utils.py
inceptor-0.1.6.dist-info/LICENSE
inceptor-0.1.6.dist-info/METADATA
inceptor-0.1.6.dist-info/WHEEL
inceptor-0.1.6.dist-info/entry_points.txt
inceptor-0.1.6.dist-info/RECORD
