Metadata-Version: 2.3
Name: inceptor
Version: 0.1.6
Summary: Multi-Level Solution Architecture Generator powered by Ollama Mistral:7b
License: Apache-2.0
Keywords: ai,architecture,llm,ollama,solution-generator,mistral
Author: Tom Sapletta
Author-email: info@softreck.dev
Requires-Python: >=3.9,<4.0
Classifier: Development Status :: 3 - Alpha
Classifier: Intended Audience :: Developers
Classifier: Intended Audience :: System Administrators
Classifier: License :: OSI Approved :: Apache Software License
Classifier: Operating System :: OS Independent
Classifier: Programming Language :: Python :: 3
Classifier: Programming Language :: Python :: 3.9
Classifier: Programming Language :: Python :: 3.10
Classifier: Programming Language :: Python :: 3.11
Classifier: Programming Language :: Python :: 3.12
Classifier: Programming Language :: Python :: 3.13
Classifier: Programming Language :: Python :: 3.8
Classifier: Topic :: Scientific/Engineering :: Artificial Intelligence
Classifier: Topic :: Software Development :: Code Generators
Classifier: Topic :: System :: Systems Administration
Provides-Extra: cli
Provides-Extra: cloud
Provides-Extra: dev
Provides-Extra: export
Provides-Extra: server
Provides-Extra: visualization
Requires-Dist: click (>=8.1.7,<9.0.0) ; extra == "cli"
Requires-Dist: dataclasses-json (>=0.6.3,<0.7.0)
Requires-Dist: fastapi (>=0.104.0,<0.105.0) ; extra == "server"
Requires-Dist: jinja2 (>=3.1.2,<4.0.0) ; extra == "export"
Requires-Dist: mkdocs-material-extensions (>=1.3.1,<2.0.0)
Requires-Dist: mkdocs-material[imaging] (>=9.6.14,<10.0.0) ; extra == "dev"
Requires-Dist: pathlib (>=1.0.1,<2.0.0)
Requires-Dist: pydantic (>=2.5.0,<3.0.0)
Requires-Dist: python-dotenv (>=1.0.0,<2.0.0) ; extra == "cli"
Requires-Dist: python-multipart (>=0.0.6,<0.0.7) ; extra == "cli"
Requires-Dist: pyyaml (>=6.0.1,<7.0.0) ; extra == "cli"
Requires-Dist: requests (>=2.31.0,<3.0.0)
Requires-Dist: rich (>=13.7.0,<14.0.0) ; extra == "cli"
Requires-Dist: tabulate (>=0.9.0,<0.10.0) ; extra == "cli"
Requires-Dist: typing-extensions (>=4.8.0,<5.0.0)
Requires-Dist: uvicorn (>=0.24.0,<0.25.0) ; extra == "server"
Project-URL: Bug Tracker, https://github.com/wronai/inceptor/issues
Project-URL: Changelog, https://github.com/wronai/inceptor/blob/main/CHANGELOG.md
Project-URL: Documentation, https://wronai.github.io/inceptor
Project-URL: Discussions, https://github.com/wronai/inceptor/discussions
Project-URL: Homepage, https://github.com/wronai/inceptor
Project-URL: Repository, https://github.com/wronai/inceptor
